tsenum/__init__.py
tsenum/cli.py
tsenum-1.2.0.dist-info/METADATA
tsenum-1.2.0.dist-info/WHEEL
tsenum-1.2.0.dist-info/entry_points.txt
tsenum-1.2.0.dist-info/licenses/LICENSE
tsenum-1.2.0.dist-info/RECORD
