Metadata-Version: 2.1
Name: tsenum
Version: 1.2.0
Summary:  Timestamp enumerator
Project-URL: Documentation, https://github.com/aboehm/tsenum#readme
Project-URL: Issues, https://github.com/aboehm/tsenum/issues
Project-URL: Source, https://github.com/aboehm/tsenum
Author-email: Alexander Böhm <alexander.boehm@malbolge.net>
License-Expression: GPL-2.0-or-later
License-File: LICENSE
Keywords: enumerator,timestamp,tool
Classifier: Development Status :: 4 - Beta
Classifier: Programming Language :: Python
Classifier: Programming Language :: Python :: 3.7
Classifier: Programming Language :: Python :: 3.8
Classifier: Programming Language :: Python :: 3.9
Classifier: Programming Language :: Python :: 3.10
Classifier: Programming Language :: Python :: 3.11
Classifier: Programming Language :: Python :: Implementation :: CPython
Classifier: Programming Language :: Python :: Implementation :: PyPy
Classifier: Topic :: Utilities
Requires-Python: >=3.7
